airflow_wingman/__init__.py
airflow_wingman/llm_client.py
airflow_wingman/llms_models.py
airflow_wingman/notes.py
airflow_wingman/plugin.py
airflow_wingman/prompt_engineering.py
airflow_wingman/views.py
airflow_wingman/providers/__init__.py
airflow_wingman/providers/anthropic_provider.py
airflow_wingman/providers/base.py
airflow_wingman/providers/google_provider.py
airflow_wingman/providers/openai_provider.py
airflow_wingman/static/css/wingman_chat.css
airflow_wingman/static/js/wingman_chat.js
airflow_wingman/templates/wingman_chat.html
airflow_wingman/tools/__init__.py
airflow_wingman/tools/conversion.py
airflow_wingman/tools/execution.py
airflow_wingman-0.4.0.dist-info/METADATA
airflow_wingman-0.4.0.dist-info/WHEEL
airflow_wingman-0.4.0.dist-info/entry_points.txt
airflow_wingman-0.4.0.dist-info/licenses/LICENSE
airflow_wingman-0.4.0.dist-info/RECORD
